pimpamqueues/__init__.py
pimpamqueues/bucketqueue.py
pimpamqueues/exceptions.py
pimpamqueues/simplequeue.py
pimpamqueues/smartqueue.py
pimpamqueues-1.0.1.dist-info/DESCRIPTION.rst
pimpamqueues-1.0.1.dist-info/METADATA
pimpamqueues-1.0.1.dist-info/metadata.json
pimpamqueues-1.0.1.dist-info/RECORD
pimpamqueues-1.0.1.dist-info/top_level.txt
pimpamqueues-1.0.1.dist-info/WHEEL
