Metadata-Version: 2.0
Name: pimpamqueues
Version: 1.0.1
Summary: Lightweight queue interfaces with Redis super powers for distributed and non-distributed systems
Home-page: https://github.com/jordimarinvalle/pimpamqueues
Author: Jordi Marín Valle
Author-email: py.jordi@gmail.com
License: MIT
Keywords: queue,queues,distributed system,distributed systems,redis,lua
Platform: all
Classifier: Development Status :: 5 - Production/Stable
Classifier: Intended Audience :: Developers
Classifier: License :: OSI Approved :: MIT License
Classifier: Programming Language :: Python :: 2
Classifier: Programming Language :: Python :: 2.7
Classifier: Programming Language :: Python :: 3
Classifier: Programming Language :: Python :: 3.4
Classifier: Topic :: System :: Distributed Computing
Classifier: Topic :: Utilities
Requires-Dist: redis
Provides-Extra: testing
Requires-Dist: pytest; extra == 'testing'
Provides-Extra: redis
Requires-Dist: redis; extra == 'redis'
